{
 "Calendrier" : [
	 {
	  "fajr": "6:28",
	  "cherouk": "7:58",
	  "dohr": "12:54",
	  "asr": "15:32",
	  "magreb": "17:53",
	  "icha": "19:15"
	 },
	 {
	  "fajr": "6:28",
	  "cherouk": "7:58",
	  "dohr": "12:54",
	  "asr": "15:33",
	  "magreb": "17:54",
	  "icha": "19:16"
	 },
	 {
	  "fajr": "6:28",
	  "cherouk": "7:58",
	  "dohr": "12:55",
	  "asr": "15:34",
	  "magreb": "17:55",
	  "icha": "19:17"
	 },
	 {
	  "fajr": "6:28",
	  "cherouk": "7:58",
	  "dohr": "12:55",
	  "asr": "15:34",
	  "magreb": "17:56",
	  "icha": "19:17"
	 },
	 {
	  "fajr": "6:29",
	  "cherouk": "7:58",
	  "dohr": "12:56",
	  "asr": "15:35",
	  "magreb": "17:56",
	  "icha": "19:18"
	 },
	 {
	  "fajr": "6:29",
	  "cherouk": "7:58",
	  "dohr": "12:56",
	  "asr": "15:36",
	  "magreb": "17:57",
	  "icha": "19:19"
	 },
	 {
	  "fajr": "6:29",
	  "cherouk": "7:58",
	  "dohr": "12:57",
	  "asr": "15:37",
	  "magreb": "17:58",
	  "icha": "19:20"
	 },
	 {
	  "fajr": "6:29",
	  "cherouk": "7:58",
	  "dohr": "12:57",
	  "asr": "15:38",
	  "magreb": "17:59",
	  "icha": "19:20"
	 },
	 {
	  "fajr": "6:29",
	  "cherouk": "7:58",
	  "dohr": "12:57",
	  "asr": "15:38",
	  "magreb": "18:00",
	  "icha": "19:21"
	 },
	 {
	  "fajr": "6:29",
	  "cherouk": "7:58",
	  "dohr": "12:58",
	  "asr": "15:39",
	  "magreb": "18:01",
	  "icha": "19:22"
	 },
	 {
	  "fajr": "6:29",
	  "cherouk": "7:58",
	  "dohr": "12:58",
	  "asr": "15:40",
	  "magreb": "18:02",
	  "icha": "19:23"
	 },
	 {
	  "fajr": "6:29",
	  "cherouk": "7:58",
	  "dohr": "12:59",
	  "asr": "15:41",
	  "magreb": "18:03",
	  "icha": "19:24"
	 },
	 {
	  "fajr": "6:29",
	  "cherouk": "7:58",
	  "dohr": "12:59",
	  "asr": "15:42",
	  "magreb": "18:04",
	  "icha": "19:24"
	 },
	 {
	  "fajr": "6:29",
	  "cherouk": "7:58",
	  "dohr": "12:59",
	  "asr": "15:42",
	  "magreb": "18:05",
	  "icha": "19:25"
	 },
	 {
	  "fajr": "6:29",
	  "cherouk": "7:57",
	  "dohr": "13:00",
	  "asr": "15:43",
	  "magreb": "18:05",
	  "icha": "19:26"
	 },
	 {
	  "fajr": "6:29",
	  "cherouk": "7:57",
	  "dohr": "13:00",
	  "asr": "15:44",
	  "magreb": "18:06",
	  "icha": "19:27"
	 },
	 {
	  "fajr": "6:28",
	  "cherouk": "7:57",
	  "dohr": "13:00",
	  "asr": "15:45",
	  "magreb": "18:07",
	  "icha": "19:28"
	 },
	 {
	  "fajr": "6:28",
	  "cherouk": "7:57",
	  "dohr": "13:01",
	  "asr": "15:46",
	  "magreb": "18:08",
	  "icha": "19:29"
	 },
	 {
	  "fajr": "6:28",
	  "cherouk": "7:56",
	  "dohr": "13:01",
	  "asr": "15:47",
	  "magreb": "18:09",
	  "icha": "19:29"
	 },
	 {
	  "fajr": "6:28",
	  "cherouk": "7:56",
	  "dohr": "13:01",
	  "asr": "15:48",
	  "magreb": "18:10",
	  "icha": "19:30"
	 },
	 {
	  "fajr": "6:28",
	  "cherouk": "7:55",
	  "dohr": "13:02",
	  "asr": "15:49",
	  "magreb": "18:11",
	  "icha": "19:31"
	 },
	 {
	  "fajr": "6:27",
	  "cherouk": "7:55",
	  "dohr": "13:02",
	  "asr": "15:49",
	  "magreb": "18:12",
	  "icha": "19:32"
	 },
	 {
	  "fajr": "6:27",
	  "cherouk": "7:54",
	  "dohr": "13:02",
	  "asr": "15:50",
	  "magreb": "18:13",
	  "icha": "19:33"
	 },
	 {
	  "fajr": "6:27",
	  "cherouk": "7:54",
	  "dohr": "13:03",
	  "asr": "15:51",
	  "magreb": "18:14",
	  "icha": "19:34"
	 },
	 {
	  "fajr": "6:26",
	  "cherouk": "7:53",
	  "dohr": "13:03",
	  "asr": "15:52",
	  "magreb": "18:15",
	  "icha": "19:35"
	 },
	 {
	  "fajr": "6:26",
	  "cherouk": "7:53",
	  "dohr": "13:03",
	  "asr": "15:53",
	  "magreb": "18:16",
	  "icha": "19:36"
	 },
	 {
	  "fajr": "6:25",
	  "cherouk": "7:52",
	  "dohr": "13:03",
	  "asr": "15:54",
	  "magreb": "18:17",
	  "icha": "19:36"
	 },
	 {
	  "fajr": "6:25",
	  "cherouk": "7:52",
	  "dohr": "13:03",
	  "asr": "15:55",
	  "magreb": "18:18",
	  "icha": "19:37"
	 },
	 {
	  "fajr": "6:24",
	  "cherouk": "7:51",
	  "dohr": "13:04",
	  "asr": "15:55",
	  "magreb": "18:19",
	  "icha": "19:38"
	 },
	 {
	  "fajr": "6:24",
	  "cherouk": "7:50",
	  "dohr": "13:04",
	  "asr": "15:56",
	  "magreb": "18:20",
	  "icha": "19:39"
	 },
	 {
	  "fajr": "6:23",
	  "cherouk": "7:50",
	  "dohr": "13:04",
	  "asr": "15:57",
	  "magreb": "18:21",
	  "icha": "19:40"
	 },
	 {
	  "fajr": "6:23",
	  "cherouk": "7:49",
	  "dohr": "13:04",
	  "asr": "15:58",
	  "magreb": "18:22",
	  "icha": "19:41"
	 },
	 {
	  "fajr": "6:22",
	  "cherouk": "7:48",
	  "dohr": "13:04",
	  "asr": "15:59",
	  "magreb": "18:23",
	  "icha": "19:42"
	 },
	 {
	  "fajr": "6:21",
	  "cherouk": "7:47",
	  "dohr": "13:04",
	  "asr": "16:00",
	  "magreb": "18:24",
	  "icha": "19:43"
	 },
	 {
	  "fajr": "6:21",
	  "cherouk": "7:47",
	  "dohr": "13:04",
	  "asr": "16:00",
	  "magreb": "18:25",
	  "icha": "19:44"
	 },
	 {
	  "fajr": "6:20",
	  "cherouk": "7:46",
	  "dohr": "13:04",
	  "asr": "16:01",
	  "magreb": "18:26",
	  "icha": "19:44"
	 },
	 {
	  "fajr": "6:19",
	  "cherouk": "7:45",
	  "dohr": "13:05",
	  "asr": "16:02",
	  "magreb": "18:27",
	  "icha": "19:45"
	 },
	 {
	  "fajr": "6:19",
	  "cherouk": "7:44",
	  "dohr": "13:05",
	  "asr": "16:03",
	  "magreb": "18:28",
	  "icha": "19:46"
	 },
	 {
	  "fajr": "6:18",
	  "cherouk": "7:43",
	  "dohr": "13:05",
	  "asr": "16:04",
	  "magreb": "18:29",
	  "icha": "19:47"
	 },
	 {
	  "fajr": "6:17",
	  "cherouk": "7:42",
	  "dohr": "13:05",
	  "asr": "16:04",
	  "magreb": "18:30",
	  "icha": "19:48"
	 },
	 {
	  "fajr": "6:16",
	  "cherouk": "7:41",
	  "dohr": "13:05",
	  "asr": "16:05",
	  "magreb": "18:31",
	  "icha": "19:49"
	 },
	 {
	  "fajr": "6:15",
	  "cherouk": "7:40",
	  "dohr": "13:05",
	  "asr": "16:06",
	  "magreb": "18:32",
	  "icha": "19:50"
	 },
	 {
	  "fajr": "6:15",
	  "cherouk": "7:39",
	  "dohr": "13:05",
	  "asr": "16:07",
	  "magreb": "18:33",
	  "icha": "19:51"
	 },
	 {
	  "fajr": "6:14",
	  "cherouk": "7:38",
	  "dohr": "13:05",
	  "asr": "16:07",
	  "magreb": "18:34",
	  "icha": "19:51"
	 },
	 {
	  "fajr": "6:13",
	  "cherouk": "7:37",
	  "dohr": "13:05",
	  "asr": "16:08",
	  "magreb": "18:35",
	  "icha": "19:52"
	 },
	 {
	  "fajr": "6:12",
	  "cherouk": "7:36",
	  "dohr": "13:05",
	  "asr": "16:09",
	  "magreb": "18:36",
	  "icha": "19:53"
	 },
	 {
	  "fajr": "6:11",
	  "cherouk": "7:35",
	  "dohr": "13:05",
	  "asr": "16:09",
	  "magreb": "18:37",
	  "icha": "19:54"
	 },
	 {
	  "fajr": "6:10",
	  "cherouk": "7:34",
	  "dohr": "13:04",
	  "asr": "16:10",
	  "magreb": "18:38",
	  "icha": "19:55"
	 },
	 {
	  "fajr": "6:09",
	  "cherouk": "7:33",
	  "dohr": "13:04",
	  "asr": "16:11",
	  "magreb": "18:39",
	  "icha": "19:56"
	 },
	 {
	  "fajr": "6:08",
	  "cherouk": "7:32",
	  "dohr": "13:04",
	  "asr": "16:11",
	  "magreb": "18:40",
	  "icha": "19:57"
	 },
	 {
	  "fajr": "6:07",
	  "cherouk": "7:31",
	  "dohr": "13:04",
	  "asr": "16:12",
	  "magreb": "18:41",
	  "icha": "19:57"
	 },
	 {
	  "fajr": "6:06",
	  "cherouk": "7:30",
	  "dohr": "13:04",
	  "asr": "16:13",
	  "magreb": "18:42",
	  "icha": "19:58"
	 },
	 {
	  "fajr": "6:05",
	  "cherouk": "7:29",
	  "dohr": "13:04",
	  "asr": "16:13",
	  "magreb": "18:43",
	  "icha": "19:59"
	 },
	 {
	  "fajr": "6:03",
	  "cherouk": "7:27",
	  "dohr": "13:04",
	  "asr": "16:14",
	  "magreb": "18:44",
	  "icha": "20:00"
	 },
	 {
	  "fajr": "6:02",
	  "cherouk": "7:26",
	  "dohr": "13:04",
	  "asr": "16:15",
	  "magreb": "18:45",
	  "icha": "20:01"
	 },
	 {
	  "fajr": "6:01",
	  "cherouk": "7:25",
	  "dohr": "13:04",
	  "asr": "16:15",
	  "magreb": "18:46",
	  "icha": "20:02"
	 },
	 {
	  "fajr": "6:00",
	  "cherouk": "7:24",
	  "dohr": "13:03",
	  "asr": "16:16",
	  "magreb": "18:46",
	  "icha": "20:02"
	 },
	 {
	  "fajr": "5:59",
	  "cherouk": "7:23",
	  "dohr": "13:03",
	  "asr": "16:16",
	  "magreb": "18:47",
	  "icha": "20:03"
	 },
	 {
	  "fajr": "5:58",
	  "cherouk": "7:21",
	  "dohr": "13:03",
	  "asr": "16:17",
	  "magreb": "18:48",
	  "icha": "20:04"
	 },
	 {
	  "fajr": "5:56",
	  "cherouk": "7:20",
	  "dohr": "13:03",
	  "asr": "16:17",
	  "magreb": "18:49",
	  "icha": "20:05"
	 },
	 {
	  "fajr": "5:55",
	  "cherouk": "7:19",
	  "dohr": "13:03",
	  "asr": "16:18",
	  "magreb": "18:50",
	  "icha": "20:06"
	 },
	 {
	  "fajr": "5:54",
	  "cherouk": "7:18",
	  "dohr": "13:02",
	  "asr": "16:18",
	  "magreb": "18:51",
	  "icha": "20:07"
	 },
	 {
	  "fajr": "5:53",
	  "cherouk": "7:16",
	  "dohr": "13:02",
	  "asr": "16:19",
	  "magreb": "18:52",
	  "icha": "20:08"
	 },
	 {
	  "fajr": "5:51",
	  "cherouk": "7:15",
	  "dohr": "13:02",
	  "asr": "16:19",
	  "magreb": "18:53",
	  "icha": "20:08"
	 },
	 {
	  "fajr": "5:50",
	  "cherouk": "7:14",
	  "dohr": "13:02",
	  "asr": "16:20",
	  "magreb": "18:53",
	  "icha": "20:09"
	 },
	 {
	  "fajr": "5:49",
	  "cherouk": "7:12",
	  "dohr": "13:02",
	  "asr": "16:20",
	  "magreb": "18:54",
	  "icha": "20:10"
	 },
	 {
	  "fajr": "5:47",
	  "cherouk": "7:11",
	  "dohr": "13:01",
	  "asr": "16:21",
	  "magreb": "18:55",
	  "icha": "20:11"
	 },
	 {
	  "fajr": "5:46",
	  "cherouk": "7:10",
	  "dohr": "13:01",
	  "asr": "16:21",
	  "magreb": "18:56",
	  "icha": "20:12"
	 },
	 {
	  "fajr": "5:45",
	  "cherouk": "7:08",
	  "dohr": "13:01",
	  "asr": "16:21",
	  "magreb": "18:57",
	  "icha": "20:13"
	 },
	 {
	  "fajr": "5:43",
	  "cherouk": "7:07",
	  "dohr": "13:01",
	  "asr": "16:22",
	  "magreb": "18:58",
	  "icha": "20:13"
	 },
	 {
	  "fajr": "5:42",
	  "cherouk": "7:06",
	  "dohr": "13:00",
	  "asr": "16:22",
	  "magreb": "18:58",
	  "icha": "20:14"
	 },
	 {
	  "fajr": "5:41",
	  "cherouk": "7:04",
	  "dohr": "13:00",
	  "asr": "16:23",
	  "magreb": "18:59",
	  "icha": "20:15"
	 },
	 {
	  "fajr": "5:39",
	  "cherouk": "7:03",
	  "dohr": "13:00",
	  "asr": "16:23",
	  "magreb": "19:00",
	  "icha": "20:16"
	 },
	 {
	  "fajr": "5:38",
	  "cherouk": "7:02",
	  "dohr": "12:59",
	  "asr": "16:23",
	  "magreb": "19:01",
	  "icha": "20:17"
	 },
	 {
	  "fajr": "5:36",
	  "cherouk": "7:00",
	  "dohr": "12:59",
	  "asr": "16:24",
	  "magreb": "19:02",
	  "icha": "20:18"
	 },
	 {
	  "fajr": "5:35",
	  "cherouk": "6:59",
	  "dohr": "12:59",
	  "asr": "16:24",
	  "magreb": "19:02",
	  "icha": "20:19"
	 },
	 {
	  "fajr": "5:33",
	  "cherouk": "6:57",
	  "dohr": "12:59",
	  "asr": "16:24",
	  "magreb": "19:03",
	  "icha": "20:19"
	 },
	 {
	  "fajr": "5:32",
	  "cherouk": "6:56",
	  "dohr": "12:58",
	  "asr": "16:25",
	  "magreb": "19:04",
	  "icha": "20:20"
	 },
	 {
	  "fajr": "5:31",
	  "cherouk": "6:55",
	  "dohr": "12:58",
	  "asr": "16:25",
	  "magreb": "19:05",
	  "icha": "20:21"
	 },
	 {
	  "fajr": "5:29",
	  "cherouk": "6:53",
	  "dohr": "12:58",
	  "asr": "16:25",
	  "magreb": "19:06",
	  "icha": "20:22"
	 },
	 {
	  "fajr": "5:28",
	  "cherouk": "6:52",
	  "dohr": "12:57",
	  "asr": "16:26",
	  "magreb": "19:06",
	  "icha": "20:23"
	 },
	 {
	  "fajr": "5:26",
	  "cherouk": "6:50",
	  "dohr": "12:57",
	  "asr": "16:26",
	  "magreb": "19:07",
	  "icha": "20:24"
	 },
	 {
	  "fajr": "5:25",
	  "cherouk": "6:49",
	  "dohr": "12:57",
	  "asr": "16:26",
	  "magreb": "19:08",
	  "icha": "20:25"
	 },
	 {
	  "fajr": "5:23",
	  "cherouk": "6:48",
	  "dohr": "12:57",
	  "asr": "16:26",
	  "magreb": "19:09",
	  "icha": "20:26"
	 },
	 {
	  "fajr": "5:22",
	  "cherouk": "6:46",
	  "dohr": "12:56",
	  "asr": "16:27",
	  "magreb": "19:10",
	  "icha": "20:26"
	 },
	 {
	  "fajr": "5:20",
	  "cherouk": "6:45",
	  "dohr": "12:56",
	  "asr": "16:27",
	  "magreb": "19:10",
	  "icha": "20:27"
	 },
	 {
	  "fajr": "5:19",
	  "cherouk": "6:44",
	  "dohr": "12:56",
	  "asr": "16:27",
	  "magreb": "19:11",
	  "icha": "20:28"
	 },
	 {
	  "fajr": "5:17",
	  "cherouk": "6:42",
	  "dohr": "12:55",
	  "asr": "16:27",
	  "magreb": "19:12",
	  "icha": "20:29"
	 },
	 {
	  "fajr": "5:16",
	  "cherouk": "6:41",
	  "dohr": "12:55",
	  "asr": "16:27",
	  "magreb": "19:13",
	  "icha": "20:30"
	 },
	 {
	  "fajr": "5:14",
	  "cherouk": "6:39",
	  "dohr": "12:55",
	  "asr": "16:28",
	  "magreb": "19:14",
	  "icha": "20:31"
	 },
	 {
	  "fajr": "5:12",
	  "cherouk": "6:38",
	  "dohr": "12:54",
	  "asr": "16:28",
	  "magreb": "19:14",
	  "icha": "20:32"
	 },
	 {
	  "fajr": "5:11",
	  "cherouk": "6:37",
	  "dohr": "12:54",
	  "asr": "16:28",
	  "magreb": "19:15",
	  "icha": "20:33"
	 },
	 {
	  "fajr": "5:09",
	  "cherouk": "6:35",
	  "dohr": "12:54",
	  "asr": "16:28",
	  "magreb": "19:16",
	  "icha": "20:34"
	 },
	 {
	  "fajr": "5:08",
	  "cherouk": "6:34",
	  "dohr": "12:54",
	  "asr": "16:28",
	  "magreb": "19:17",
	  "icha": "20:35"
	 },
	 {
	  "fajr": "5:06",
	  "cherouk": "6:33",
	  "dohr": "12:53",
	  "asr": "16:28",
	  "magreb": "19:17",
	  "icha": "20:36"
	 },
	 {
	  "fajr": "5:05",
	  "cherouk": "6:31",
	  "dohr": "12:53",
	  "asr": "16:29",
	  "magreb": "19:18",
	  "icha": "20:37"
	 },
	 {
	  "fajr": "5:03",
	  "cherouk": "6:30",
	  "dohr": "12:53",
	  "asr": "16:29",
	  "magreb": "19:19",
	  "icha": "20:38"
	 },
	 {
	  "fajr": "5:02",
	  "cherouk": "6:28",
	  "dohr": "12:52",
	  "asr": "16:29",
	  "magreb": "19:20",
	  "icha": "20:39"
	 },
	 {
	  "fajr": "5:00",
	  "cherouk": "6:27",
	  "dohr": "12:52",
	  "asr": "16:29",
	  "magreb": "19:21",
	  "icha": "20:40"
	 },
	 {
	  "fajr": "4:59",
	  "cherouk": "6:26",
	  "dohr": "12:52",
	  "asr": "16:29",
	  "magreb": "19:21",
	  "icha": "20:41"
	 },
	 {
	  "fajr": "4:57",
	  "cherouk": "6:25",
	  "dohr": "12:52",
	  "asr": "16:29",
	  "magreb": "19:22",
	  "icha": "20:42"
	 },
	 {
	  "fajr": "4:55",
	  "cherouk": "6:23",
	  "dohr": "12:51",
	  "asr": "16:29",
	  "magreb": "19:23",
	  "icha": "20:43"
	 },
	 {
	  "fajr": "4:54",
	  "cherouk": "6:22",
	  "dohr": "12:51",
	  "asr": "16:30",
	  "magreb": "19:24",
	  "icha": "20:44"
	 },
	 {
	  "fajr": "4:52",
	  "cherouk": "6:21",
	  "dohr": "12:51",
	  "asr": "16:30",
	  "magreb": "19:25",
	  "icha": "20:45"
	 },
	 {
	  "fajr": "4:51",
	  "cherouk": "6:19",
	  "dohr": "12:51",
	  "asr": "16:30",
	  "magreb": "19:25",
	  "icha": "20:46"
	 },
	 {
	  "fajr": "4:49",
	  "cherouk": "6:18",
	  "dohr": "12:50",
	  "asr": "16:30",
	  "magreb": "19:26",
	  "icha": "20:47"
	 },
	 {
	  "fajr": "4:48",
	  "cherouk": "6:17",
	  "dohr": "12:50",
	  "asr": "16:30",
	  "magreb": "19:27",
	  "icha": "20:48"
	 },
	 {
	  "fajr": "4:46",
	  "cherouk": "6:16",
	  "dohr": "12:50",
	  "asr": "16:30",
	  "magreb": "19:28",
	  "icha": "20:49"
	 },
	 {
	  "fajr": "4:45",
	  "cherouk": "6:14",
	  "dohr": "12:50",
	  "asr": "16:30",
	  "magreb": "19:29",
	  "icha": "20:50"
	 },
	 {
	  "fajr": "4:43",
	  "cherouk": "6:13",
	  "dohr": "12:49",
	  "asr": "16:30",
	  "magreb": "19:29",
	  "icha": "20:51"
	 },
	 {
	  "fajr": "4:42",
	  "cherouk": "6:12",
	  "dohr": "12:49",
	  "asr": "16:30",
	  "magreb": "19:30",
	  "icha": "20:52"
	 },
	 {
	  "fajr": "4:41",
	  "cherouk": "6:11",
	  "dohr": "12:49",
	  "asr": "16:30",
	  "magreb": "19:31",
	  "icha": "20:52"
	 },
	 {
	  "fajr": "4:40",
	  "cherouk": "6:10",
	  "dohr": "12:49",
	  "asr": "16:30",
	  "magreb": "19:32",
	  "icha": "20:53"
	 },
	 {
	  "fajr": "4:38",
	  "cherouk": "6:08",
	  "dohr": "12:49",
	  "asr": "16:31",
	  "magreb": "19:33",
	  "icha": "20:54"
	 },
	 {
	  "fajr": "4:37",
	  "cherouk": "6:07",
	  "dohr": "12:48",
	  "asr": "16:31",
	  "magreb": "19:33",
	  "icha": "20:55"
	 },
	 {
	  "fajr": "4:36",
	  "cherouk": "6:06",
	  "dohr": "12:48",
	  "asr": "16:31",
	  "magreb": "19:34",
	  "icha": "20:56"
	 },
	 {
	  "fajr": "4:34",
	  "cherouk": "6:05",
	  "dohr": "12:48",
	  "asr": "16:31",
	  "magreb": "19:35",
	  "icha": "20:57"
	 },
	 {
	  "fajr": "4:33",
	  "cherouk": "6:04",
	  "dohr": "12:48",
	  "asr": "16:31",
	  "magreb": "19:36",
	  "icha": "20:58"
	 },
	 {
	  "fajr": "4:31",
	  "cherouk": "6:03",
	  "dohr": "12:48",
	  "asr": "16:31",
	  "magreb": "19:36",
	  "icha": "21:00"
	 },
	 {
	  "fajr": "4:30",
	  "cherouk": "6:02",
	  "dohr": "12:48",
	  "asr": "16:31",
	  "magreb": "19:37",
	  "icha": "21:01"
	 },
	 {
	  "fajr": "4:29",
	  "cherouk": "6:01",
	  "dohr": "12:48",
	  "asr": "16:31",
	  "magreb": "19:38",
	  "icha": "21:02"
	 },
	 {
	  "fajr": "4:27",
	  "cherouk": "6:00",
	  "dohr": "12:48",
	  "asr": "16:31",
	  "magreb": "19:39",
	  "icha": "21:03"
	 },
	 {
	  "fajr": "4:26",
	  "cherouk": "5:59",
	  "dohr": "12:47",
	  "asr": "16:31",
	  "magreb": "19:40",
	  "icha": "21:04"
	 },
	 {
	  "fajr": "4:24",
	  "cherouk": "5:58",
	  "dohr": "12:47",
	  "asr": "16:31",
	  "magreb": "19:40",
	  "icha": "21:05"
	 },
	 {
	  "fajr": "4:23",
	  "cherouk": "5:57",
	  "dohr": "12:47",
	  "asr": "16:31",
	  "magreb": "19:41",
	  "icha": "21:06"
	 },
	 {
	  "fajr": "4:22",
	  "cherouk": "5:56",
	  "dohr": "12:47",
	  "asr": "16:32",
	  "magreb": "19:42",
	  "icha": "21:07"
	 },
	 {
	  "fajr": "4:21",
	  "cherouk": "5:55",
	  "dohr": "12:47",
	  "asr": "16:32",
	  "magreb": "19:43",
	  "icha": "21:08"
	 },
	 {
	  "fajr": "4:19",
	  "cherouk": "5:54",
	  "dohr": "12:47",
	  "asr": "16:32",
	  "magreb": "19:44",
	  "icha": "21:09"
	 },
	 {
	  "fajr": "4:18",
	  "cherouk": "5:53",
	  "dohr": "12:47",
	  "asr": "16:32",
	  "magreb": "19:44",
	  "icha": "21:11"
	 },
	 {
	  "fajr": "4:17",
	  "cherouk": "5:52",
	  "dohr": "12:47",
	  "asr": "16:32",
	  "magreb": "19:45",
	  "icha": "21:12"
	 },
	 {
	  "fajr": "4:16",
	  "cherouk": "5:51",
	  "dohr": "12:47",
	  "asr": "16:32",
	  "magreb": "19:46",
	  "icha": "21:13"
	 },
	 {
	  "fajr": "4:14",
	  "cherouk": "5:50",
	  "dohr": "12:47",
	  "asr": "16:32",
	  "magreb": "19:47",
	  "icha": "21:14"
	 },
	 {
	  "fajr": "4:13",
	  "cherouk": "5:50",
	  "dohr": "12:47",
	  "asr": "16:32",
	  "magreb": "19:48",
	  "icha": "21:15"
	 },
	 {
	  "fajr": "4:12",
	  "cherouk": "5:49",
	  "dohr": "12:47",
	  "asr": "16:32",
	  "magreb": "19:48",
	  "icha": "21:16"
	 },
	 {
	  "fajr": "4:11",
	  "cherouk": "5:48",
	  "dohr": "12:47",
	  "asr": "16:32",
	  "magreb": "19:49",
	  "icha": "21:17"
	 },
	 {
	  "fajr": "4:10",
	  "cherouk": "5:47",
	  "dohr": "12:47",
	  "asr": "16:33",
	  "magreb": "19:50",
	  "icha": "21:18"
	 },
	 {
	  "fajr": "4:09",
	  "cherouk": "5:47",
	  "dohr": "12:47",
	  "asr": "16:33",
	  "magreb": "19:51",
	  "icha": "21:19"
	 },
	 {
	  "fajr": "4:08",
	  "cherouk": "5:46",
	  "dohr": "12:47",
	  "asr": "16:33",
	  "magreb": "19:51",
	  "icha": "21:20"
	 },
	 {
	  "fajr": "4:07",
	  "cherouk": "5:45",
	  "dohr": "12:47",
	  "asr": "16:33",
	  "magreb": "19:52",
	  "icha": "21:21"
	 },
	 {
	  "fajr": "4:06",
	  "cherouk": "5:45",
	  "dohr": "12:47",
	  "asr": "16:33",
	  "magreb": "19:53",
	  "icha": "21:22"
	 },
	 {
	  "fajr": "4:05",
	  "cherouk": "5:44",
	  "dohr": "12:47",
	  "asr": "16:33",
	  "magreb": "19:53",
	  "icha": "21:24"
	 },
	 {
	  "fajr": "4:04",
	  "cherouk": "5:43",
	  "dohr": "12:47",
	  "asr": "16:33",
	  "magreb": "19:53",
	  "icha": "21:25"
	 },
	 {
	  "fajr": "4:03",
	  "cherouk": "5:43",
	  "dohr": "12:47",
	  "asr": "16:33",
	  "magreb": "19:54",
	  "icha": "21:26"
	 },
	 {
	  "fajr": "4:02",
	  "cherouk": "5:42",
	  "dohr": "12:47",
	  "asr": "16:34",
	  "magreb": "19:55",
	  "icha": "21:27"
	 },
	 {
	  "fajr": "4:01",
	  "cherouk": "5:42",
	  "dohr": "12:47",
	  "asr": "16:34",
	  "magreb": "19:55",
	  "icha": "21:28"
	 },
	 {
	  "fajr": "4:01",
	  "cherouk": "5:41",
	  "dohr": "12:48",
	  "asr": "16:34",
	  "magreb": "19:56",
	  "icha": "21:28"
	 },
	 {
	  "fajr": "4:00",
	  "cherouk": "5:41",
	  "dohr": "12:48",
	  "asr": "16:34",
	  "magreb": "19:57",
	  "icha": "21:29"
	 },
	 {
	  "fajr": "3:59",
	  "cherouk": "5:40",
	  "dohr": "12:48",
	  "asr": "16:34",
	  "magreb": "19:58",
	  "icha": "21:30"
	 },
	 {
	  "fajr": "3:58",
	  "cherouk": "5:40",
	  "dohr": "12:48",
	  "asr": "16:34",
	  "magreb": "19:58",
	  "icha": "21:31"
	 },
	 {
	  "fajr": "3:58",
	  "cherouk": "5:39",
	  "dohr": "12:48",
	  "asr": "16:35",
	  "magreb": "19:59",
	  "icha": "21:32"
	 },
	 {
	  "fajr": "3:57",
	  "cherouk": "5:39",
	  "dohr": "12:48",
	  "asr": "16:35",
	  "magreb": "19:59",
	  "icha": "21:33"
	 },
	 {
	  "fajr": "3:56",
	  "cherouk": "5:39",
	  "dohr": "12:48",
	  "asr": "16:35",
	  "magreb": "20:00",
	  "icha": "21:34"
	 },
	 {
	  "fajr": "3:56",
	  "cherouk": "5:38",
	  "dohr": "12:48",
	  "asr": "16:35",
	  "magreb": "20:01",
	  "icha": "21:35"
	 },
	 {
	  "fajr": "3:55",
	  "cherouk": "5:38",
	  "dohr": "12:49",
	  "asr": "16:35",
	  "magreb": "20:01",
	  "icha": "21:36"
	 },
	 {
	  "fajr": "3:55",
	  "cherouk": "5:38",
	  "dohr": "12:49",
	  "asr": "16:35",
	  "magreb": "20:02",
	  "icha": "21:36"
	 },
	 {
	  "fajr": "3:54",
	  "cherouk": "5:38",
	  "dohr": "12:49",
	  "asr": "16:36",
	  "magreb": "20:02",
	  "icha": "21:37"
	 },
	 {
	  "fajr": "3:54",
	  "cherouk": "5:38",
	  "dohr": "12:49",
	  "asr": "16:36",
	  "magreb": "20:03",
	  "icha": "21:38"
	 },
	 {
	  "fajr": "3:54",
	  "cherouk": "5:37",
	  "dohr": "12:49",
	  "asr": "16:36",
	  "magreb": "20:03",
	  "icha": "21:38"
	 },
	 {
	  "fajr": "3:53",
	  "cherouk": "5:37",
	  "dohr": "12:49",
	  "asr": "16:36",
	  "magreb": "20:04",
	  "icha": "21:39"
	 },
	 {
	  "fajr": "3:53",
	  "cherouk": "5:37",
	  "dohr": "12:50",
	  "asr": "16:36",
	  "magreb": "20:04",
	  "icha": "21:40"
	 },
	 {
	  "fajr": "3:53",
	  "cherouk": "5:37",
	  "dohr": "12:50",
	  "asr": "16:37",
	  "magreb": "20:05",
	  "icha": "21:40"
	 },
	 {
	  "fajr": "3:53",
	  "cherouk": "5:37",
	  "dohr": "12:50",
	  "asr": "16:37",
	  "magreb": "20:05",
	  "icha": "21:41"
	 },
	 {
	  "fajr": "3:52",
	  "cherouk": "5:37",
	  "dohr": "12:50",
	  "asr": "16:37",
	  "magreb": "20:06",
	  "icha": "21:42"
	 },
	 {
	  "fajr": "3:52",
	  "cherouk": "5:37",
	  "dohr": "12:51",
	  "asr": "16:37",
	  "magreb": "20:06",
	  "icha": "21:42"
	 },
	 {
	  "fajr": "3:52",
	  "cherouk": "5:37",
	  "dohr": "12:51",
	  "asr": "16:37",
	  "magreb": "20:07",
	  "icha": "21:43"
	 },
	 {
	  "fajr": "3:52",
	  "cherouk": "5:37",
	  "dohr": "12:51",
	  "asr": "16:38",
	  "magreb": "20:07",
	  "icha": "21:43"
	 },
	 {
	  "fajr": "3:52",
	  "cherouk": "5:37",
	  "dohr": "12:51",
	  "asr": "16:38",
	  "magreb": "20:07",
	  "icha": "21:43"
	 },
	 {
	  "fajr": "3:52",
	  "cherouk": "5:37",
	  "dohr": "12:51",
	  "asr": "16:38",
	  "magreb": "20:08",
	  "icha": "21:44"
	 },
	 {
	  "fajr": "3:52",
	  "cherouk": "5:37",
	  "dohr": "12:52",
	  "asr": "16:38",
	  "magreb": "20:08",
	  "icha": "21:44"
	 },
	 {
	  "fajr": "3:52",
	  "cherouk": "5:37",
	  "dohr": "12:52",
	  "asr": "16:39",
	  "magreb": "20:08",
	  "icha": "21:44"
	 },
	 {
	  "fajr": "3:52",
	  "cherouk": "5:38",
	  "dohr": "12:52",
	  "asr": "16:39",
	  "magreb": "20:08",
	  "icha": "21:45"
	 },
	 {
	  "fajr": "3:53",
	  "cherouk": "5:38",
	  "dohr": "12:52",
	  "asr": "16:39",
	  "magreb": "20:09",
	  "icha": "21:45"
	 },
	 {
	  "fajr": "3:53",
	  "cherouk": "5:38",
	  "dohr": "12:52",
	  "asr": "16:39",
	  "magreb": "20:09",
	  "icha": "21:45"
	 },
	 {
	  "fajr": "3:53",
	  "cherouk": "5:38",
	  "dohr": "12:53",
	  "asr": "16:39",
	  "magreb": "20:09",
	  "icha": "21:45"
	 },
	 {
	  "fajr": "3:53",
	  "cherouk": "5:39",
	  "dohr": "12:53",
	  "asr": "16:40",
	  "magreb": "20:09",
	  "icha": "21:45"
	 },
	 {
	  "fajr": "3:54",
	  "cherouk": "5:39",
	  "dohr": "12:53",
	  "asr": "16:40",
	  "magreb": "20:09",
	  "icha": "21:45"
	 },
	 {
	  "fajr": "3:54",
	  "cherouk": "5:39",
	  "dohr": "12:53",
	  "asr": "16:40",
	  "magreb": "20:09",
	  "icha": "21:45"
	 },
	 {
	  "fajr": "3:54",
	  "cherouk": "5:39",
	  "dohr": "12:54",
	  "asr": "16:40",
	  "magreb": "20:09",
	  "icha": "21:45"
	 },
	 {
	  "fajr": "3:55",
	  "cherouk": "5:40",
	  "dohr": "12:54",
	  "asr": "16:40",
	  "magreb": "20:10",
	  "icha": "21:45"
	 },
	 {
	  "fajr": "3:55",
	  "cherouk": "5:40",
	  "dohr": "12:54",
	  "asr": "16:41",
	  "magreb": "20:10",
	  "icha": "21:45"
	 },
	 {
	  "fajr": "3:56",
	  "cherouk": "5:41",
	  "dohr": "12:54",
	  "asr": "16:41",
	  "magreb": "20:10",
	  "icha": "21:45"
	 },
	 {
	  "fajr": "3:56",
	  "cherouk": "5:41",
	  "dohr": "12:54",
	  "asr": "16:41",
	  "magreb": "20:09",
	  "icha": "21:45"
	 },
	 {
	  "fajr": "3:57",
	  "cherouk": "5:41",
	  "dohr": "12:55",
	  "asr": "16:41",
	  "magreb": "20:09",
	  "icha": "21:45"
	 },
	 {
	  "fajr": "3:58",
	  "cherouk": "5:42",
	  "dohr": "12:55",
	  "asr": "16:41",
	  "magreb": "20:09",
	  "icha": "21:45"
	 },
	 {
	  "fajr": "3:58",
	  "cherouk": "5:42",
	  "dohr": "12:55",
	  "asr": "16:42",
	  "magreb": "20:09",
	  "icha": "21:44"
	 },
	 {
	  "fajr": "3:59",
	  "cherouk": "5:43",
	  "dohr": "12:55",
	  "asr": "16:42",
	  "magreb": "20:09",
	  "icha": "21:44"
	 },
	 {
	  "fajr": "3:59",
	  "cherouk": "5:43",
	  "dohr": "12:55",
	  "asr": "16:42",
	  "magreb": "20:09",
	  "icha": "21:44"
	 },
	 {
	  "fajr": "4:00",
	  "cherouk": "5:44",
	  "dohr": "12:55",
	  "asr": "16:42",
	  "magreb": "20:09",
	  "icha": "21:43"
	 },
	 {
	  "fajr": "4:01",
	  "cherouk": "5:44",
	  "dohr": "12:56",
	  "asr": "16:42",
	  "magreb": "20:08",
	  "icha": "21:43"
	 },
	 {
	  "fajr": "4:02",
	  "cherouk": "5:45",
	  "dohr": "12:56",
	  "asr": "16:42",
	  "magreb": "20:08",
	  "icha": "21:42"
	 },
	 {
	  "fajr": "4:03",
	  "cherouk": "5:45",
	  "dohr": "12:56",
	  "asr": "16:42",
	  "magreb": "20:08",
	  "icha": "21:42"
	 },
	 {
	  "fajr": "4:03",
	  "cherouk": "5:46",
	  "dohr": "12:56",
	  "asr": "16:43",
	  "magreb": "20:08",
	  "icha": "21:41"
	 },
	 {
	  "fajr": "4:04",
	  "cherouk": "5:47",
	  "dohr": "12:56",
	  "asr": "16:43",
	  "magreb": "20:07",
	  "icha": "21:41"
	 },
	 {
	  "fajr": "4:05",
	  "cherouk": "5:47",
	  "dohr": "12:56",
	  "asr": "16:43",
	  "magreb": "20:07",
	  "icha": "21:40"
	 },
	 {
	  "fajr": "4:06",
	  "cherouk": "5:48",
	  "dohr": "12:56",
	  "asr": "16:43",
	  "magreb": "20:07",
	  "icha": "21:39"
	 },
	 {
	  "fajr": "4:07",
	  "cherouk": "5:48",
	  "dohr": "12:56",
	  "asr": "16:43",
	  "magreb": "20:06",
	  "icha": "21:39"
	 },
	 {
	  "fajr": "4:08",
	  "cherouk": "5:49",
	  "dohr": "12:57",
	  "asr": "16:43",
	  "magreb": "20:06",
	  "icha": "21:38"
	 },
	 {
	  "fajr": "4:09",
	  "cherouk": "5:50",
	  "dohr": "12:57",
	  "asr": "16:43",
	  "magreb": "20:05",
	  "icha": "21:37"
	 },
	 {
	  "fajr": "4:10",
	  "cherouk": "5:50",
	  "dohr": "12:57",
	  "asr": "16:43",
	  "magreb": "20:05",
	  "icha": "21:37"
	 },
	 {
	  "fajr": "4:11",
	  "cherouk": "5:51",
	  "dohr": "12:57",
	  "asr": "16:43",
	  "magreb": "20:04",
	  "icha": "21:35"
	 },
	 {
	  "fajr": "4:12",
	  "cherouk": "5:52",
	  "dohr": "12:57",
	  "asr": "16:43",
	  "magreb": "20:03",
	  "icha": "21:35"
	 },
	 {
	  "fajr": "4:13",
	  "cherouk": "5:53",
	  "dohr": "12:57",
	  "asr": "16:43",
	  "magreb": "20:03",
	  "icha": "21:34"
	 },
	 {
	  "fajr": "4:14",
	  "cherouk": "5:53",
	  "dohr": "12:57",
	  "asr": "16:43",
	  "magreb": "20:02",
	  "icha": "21:33"
	 },
	 {
	  "fajr": "4:15",
	  "cherouk": "5:54",
	  "dohr": "12:57",
	  "asr": "16:43",
	  "magreb": "20:02",
	  "icha": "21:32"
	 },
	 {
	  "fajr": "4:16",
	  "cherouk": "5:55",
	  "dohr": "12:57",
	  "asr": "16:43",
	  "magreb": "20:01",
	  "icha": "21:31"
	 },
	 {
	  "fajr": "4:17",
	  "cherouk": "5:55",
	  "dohr": "12:57",
	  "asr": "16:43",
	  "magreb": "20:00",
	  "icha": "21:30"
	 },
	 {
	  "fajr": "4:18",
	  "cherouk": "5:56",
	  "dohr": "12:57",
	  "asr": "16:43",
	  "magreb": "20:00",
	  "icha": "21:29"
	 },
	 {
	  "fajr": "4:19",
	  "cherouk": "5:57",
	  "dohr": "12:57",
	  "asr": "16:43",
	  "magreb": "19:59",
	  "icha": "21:28"
	 },
	 {
	  "fajr": "4:20",
	  "cherouk": "5:58",
	  "dohr": "12:57",
	  "asr": "16:43",
	  "magreb": "19:58",
	  "icha": "21:27"
	 },
	 {
	  "fajr": "4:21",
	  "cherouk": "5:58",
	  "dohr": "12:57",
	  "asr": "16:42",
	  "magreb": "19:57",
	  "icha": "21:26"
	 },
	 {
	  "fajr": "4:22",
	  "cherouk": "5:59",
	  "dohr": "12:57",
	  "asr": "16:42",
	  "magreb": "19:57",
	  "icha": "21:25"
	 },
	 {
	  "fajr": "4:23",
	  "cherouk": "6:00",
	  "dohr": "12:57",
	  "asr": "16:42",
	  "magreb": "19:57",
	  "icha": "21:23"
	 },
	 {
	  "fajr": "4:24",
	  "cherouk": "6:00",
	  "dohr": "12:57",
	  "asr": "16:42",
	  "magreb": "19:56",
	  "icha": "21:22"
	 },
	 {
	  "fajr": "4:26",
	  "cherouk": "6:01",
	  "dohr": "12:57",
	  "asr": "16:42",
	  "magreb": "19:55",
	  "icha": "21:21"
	 },
	 {
	  "fajr": "4:27",
	  "cherouk": "6:02",
	  "dohr": "12:57",
	  "asr": "16:42",
	  "magreb": "19:54",
	  "icha": "21:20"
	 },
	 {
	  "fajr": "4:28",
	  "cherouk": "6:03",
	  "dohr": "12:57",
	  "asr": "16:41",
	  "magreb": "19:53",
	  "icha": "21:19"
	 },
	 {
	  "fajr": "4:29",
	  "cherouk": "6:03",
	  "dohr": "12:57",
	  "asr": "16:41",
	  "magreb": "19:52",
	  "icha": "21:17"
	 },
	 {
	  "fajr": "4:30",
	  "cherouk": "6:04",
	  "dohr": "12:56",
	  "asr": "16:41",
	  "magreb": "19:51",
	  "icha": "21:16"
	 },
	 {
	  "fajr": "4:31",
	  "cherouk": "6:05",
	  "dohr": "12:56",
	  "asr": "16:41",
	  "magreb": "19:50",
	  "icha": "21:15"
	 },
	 {
	  "fajr": "4:32",
	  "cherouk": "6:06",
	  "dohr": "12:56",
	  "asr": "16:40",
	  "magreb": "19:49",
	  "icha": "21:13"
	 },
	 {
	  "fajr": "4:33",
	  "cherouk": "6:06",
	  "dohr": "12:56",
	  "asr": "16:40",
	  "magreb": "19:48",
	  "icha": "21:12"
	 },
	 {
	  "fajr": "4:34",
	  "cherouk": "6:07",
	  "dohr": "12:56",
	  "asr": "16:40",
	  "magreb": "19:47",
	  "icha": "21:11"
	 },
	 {
	  "fajr": "4:35",
	  "cherouk": "6:08",
	  "dohr": "12:56",
	  "asr": "16:39",
	  "magreb": "19:46",
	  "icha": "21:09"
	 },
	 {
	  "fajr": "4:36",
	  "cherouk": "6:09",
	  "dohr": "12:56",
	  "asr": "16:39",
	  "magreb": "19:45",
	  "icha": "21:08"
	 },
	 {
	  "fajr": "4:37",
	  "cherouk": "6:09",
	  "dohr": "12:55",
	  "asr": "16:38",
	  "magreb": "19:44",
	  "icha": "21:07"
	 },
	 {
	  "fajr": "4:38",
	  "cherouk": "6:10",
	  "dohr": "12:55",
	  "asr": "16:38",
	  "magreb": "19:43",
	  "icha": "21:05"
	 },
	 {
	  "fajr": "4:40",
	  "cherouk": "6:11",
	  "dohr": "12:55",
	  "asr": "16:38",
	  "magreb": "19:42",
	  "icha": "21:04"
	 },
	 {
	  "fajr": "4:41",
	  "cherouk": "6:12",
	  "dohr": "12:55",
	  "asr": "16:37",
	  "magreb": "19:40",
	  "icha": "21:02"
	 },
	 {
	  "fajr": "4:42",
	  "cherouk": "6:12",
	  "dohr": "12:55",
	  "asr": "16:37",
	  "magreb": "19:39",
	  "icha": "21:01"
	 },
	 {
	  "fajr": "4:43",
	  "cherouk": "6:13",
	  "dohr": "12:54",
	  "asr": "16:36",
	  "magreb": "19:38",
	  "icha": "20:59"
	 },
	 {
	  "fajr": "4:44",
	  "cherouk": "6:14",
	  "dohr": "12:54",
	  "asr": "16:36",
	  "magreb": "19:37",
	  "icha": "20:58"
	 },
	 {
	  "fajr": "4:45",
	  "cherouk": "6:15",
	  "dohr": "12:54",
	  "asr": "16:35",
	  "magreb": "19:36",
	  "icha": "20:57"
	 },
	 {
	  "fajr": "4:46",
	  "cherouk": "6:15",
	  "dohr": "12:54",
	  "asr": "16:35",
	  "magreb": "19:34",
	  "icha": "20:55"
	 },
	 {
	  "fajr": "4:47",
	  "cherouk": "6:16",
	  "dohr": "12:53",
	  "asr": "16:34",
	  "magreb": "19:33",
	  "icha": "20:54"
	 },
	 {
	  "fajr": "4:48",
	  "cherouk": "6:17",
	  "dohr": "12:53",
	  "asr": "16:34",
	  "magreb": "19:32",
	  "icha": "20:52"
	 },
	 {
	  "fajr": "4:49",
	  "cherouk": "6:17",
	  "dohr": "12:53",
	  "asr": "16:33",
	  "magreb": "19:31",
	  "icha": "20:51"
	 },
	 {
	  "fajr": "4:50",
	  "cherouk": "6:18",
	  "dohr": "12:53",
	  "asr": "16:33",
	  "magreb": "19:29",
	  "icha": "20:49"
	 },
	 {
	  "fajr": "4:51",
	  "cherouk": "6:19",
	  "dohr": "12:52",
	  "asr": "16:32",
	  "magreb": "19:28",
	  "icha": "20:48"
	 },
	 {
	  "fajr": "4:52",
	  "cherouk": "6:20",
	  "dohr": "12:52",
	  "asr": "16:31",
	  "magreb": "19:27",
	  "icha": "20:46"
	 },
	 {
	  "fajr": "4:53",
	  "cherouk": "6:20",
	  "dohr": "12:52",
	  "asr": "16:31",
	  "magreb": "19:25",
	  "icha": "20:44"
	 },
	 {
	  "fajr": "4:53",
	  "cherouk": "6:21",
	  "dohr": "12:51",
	  "asr": "16:30",
	  "magreb": "19:24",
	  "icha": "20:44"
	 },
	 {
	  "fajr": "4:54",
	  "cherouk": "6:22",
	  "dohr": "12:51",
	  "asr": "16:29",
	  "magreb": "19:23",
	  "icha": "20:42"
	 },
	 {
	  "fajr": "4:55",
	  "cherouk": "6:23",
	  "dohr": "12:51",
	  "asr": "16:29",
	  "magreb": "19:22",
	  "icha": "20:41"
	 },
	 {
	  "fajr": "4:56",
	  "cherouk": "6:23",
	  "dohr": "12:51",
	  "asr": "16:28",
	  "magreb": "19:20",
	  "icha": "20:39"
	 },
	 {
	  "fajr": "4:57",
	  "cherouk": "6:24",
	  "dohr": "12:50",
	  "asr": "16:27",
	  "magreb": "19:19",
	  "icha": "20:38"
	 },
	 {
	  "fajr": "4:57",
	  "cherouk": "6:25",
	  "dohr": "12:50",
	  "asr": "16:27",
	  "magreb": "19:17",
	  "icha": "20:36"
	 },
	 {
	  "fajr": "4:58",
	  "cherouk": "6:25",
	  "dohr": "12:50",
	  "asr": "16:26",
	  "magreb": "19:16",
	  "icha": "20:35"
	 },
	 {
	  "fajr": "4:59",
	  "cherouk": "6:26",
	  "dohr": "12:49",
	  "asr": "16:25",
	  "magreb": "19:15",
	  "icha": "20:33"
	 },
	 {
	  "fajr": "5:00",
	  "cherouk": "6:27",
	  "dohr": "12:49",
	  "asr": "16:24",
	  "magreb": "19:13",
	  "icha": "20:32"
	 },
	 {
	  "fajr": "5:01",
	  "cherouk": "6:28",
	  "dohr": "12:49",
	  "asr": "16:23",
	  "magreb": "19:12",
	  "icha": "20:30"
	 },
	 {
	  "fajr": "5:02",
	  "cherouk": "6:28",
	  "dohr": "12:48",
	  "asr": "16:23",
	  "magreb": "19:11",
	  "icha": "20:28"
	 },
	 {
	  "fajr": "5:03",
	  "cherouk": "6:29",
	  "dohr": "12:48",
	  "asr": "16:22",
	  "magreb": "19:09",
	  "icha": "20:27"
	 },
	 {
	  "fajr": "5:04",
	  "cherouk": "6:30",
	  "dohr": "12:47",
	  "asr": "16:21",
	  "magreb": "19:08",
	  "icha": "20:25"
	 },
	 {
	  "fajr": "5:05",
	  "cherouk": "6:30",
	  "dohr": "12:47",
	  "asr": "16:20",
	  "magreb": "19:06",
	  "icha": "20:24"
	 },
	 {
	  "fajr": "5:06",
	  "cherouk": "6:31",
	  "dohr": "12:47",
	  "asr": "16:19",
	  "magreb": "19:05",
	  "icha": "20:22"
	 },
	 {
	  "fajr": "5:06",
	  "cherouk": "6:32",
	  "dohr": "12:46",
	  "asr": "16:19",
	  "magreb": "19:03",
	  "icha": "20:21"
	 },
	 {
	  "fajr": "5:07",
	  "cherouk": "6:33",
	  "dohr": "12:46",
	  "asr": "16:18",
	  "magreb": "19:02",
	  "icha": "20:19"
	 },
	 {
	  "fajr": "5:08",
	  "cherouk": "6:33",
	  "dohr": "12:46",
	  "asr": "16:17",
	  "magreb": "19:01",
	  "icha": "20:17"
	 },
	 {
	  "fajr": "5:09",
	  "cherouk": "6:34",
	  "dohr": "12:45",
	  "asr": "16:16",
	  "magreb": "18:59",
	  "icha": "20:16"
	 },
	 {
	  "fajr": "5:10",
	  "cherouk": "6:35",
	  "dohr": "12:45",
	  "asr": "16:15",
	  "magreb": "18:58",
	  "icha": "20:14"
	 },
	 {
	  "fajr": "5:11",
	  "cherouk": "6:35",
	  "dohr": "12:45",
	  "asr": "16:14",
	  "magreb": "18:56",
	  "icha": "20:13"
	 },
	 {
	  "fajr": "5:11",
	  "cherouk": "6:36",
	  "dohr": "12:44",
	  "asr": "16:13",
	  "magreb": "18:55",
	  "icha": "20:11"
	 },
	 {
	  "fajr": "5:12",
	  "cherouk": "6:37",
	  "dohr": "12:44",
	  "asr": "16:12",
	  "magreb": "18:53",
	  "icha": "20:10"
	 },
	 {
	  "fajr": "5:13",
	  "cherouk": "6:38",
	  "dohr": "12:44",
	  "asr": "16:11",
	  "magreb": "18:52",
	  "icha": "20:08"
	 },
	 {
	  "fajr": "5:14",
	  "cherouk": "6:38",
	  "dohr": "12:43",
	  "asr": "16:11",
	  "magreb": "18:51",
	  "icha": "20:07"
	 },
	 {
	  "fajr": "5:15",
	  "cherouk": "6:39",
	  "dohr": "12:43",
	  "asr": "16:10",
	  "magreb": "18:49",
	  "icha": "20:05"
	 },
	 {
	  "fajr": "5:16",
	  "cherouk": "6:40",
	  "dohr": "12:43",
	  "asr": "16:09",
	  "magreb": "18:48",
	  "icha": "20:04"
	 },
	 {
	  "fajr": "5:16",
	  "cherouk": "6:40",
	  "dohr": "12:42",
	  "asr": "16:08",
	  "magreb": "18:46",
	  "icha": "20:02"
	 },
	 {
	  "fajr": "5:17",
	  "cherouk": "6:41",
	  "dohr": "12:42",
	  "asr": "16:07",
	  "magreb": "18:45",
	  "icha": "20:01"
	 },
	 {
	  "fajr": "5:18",
	  "cherouk": "6:42",
	  "dohr": "12:41",
	  "asr": "16:06",
	  "magreb": "18:43",
	  "icha": "19:59"
	 },
	 {
	  "fajr": "5:19",
	  "cherouk": "6:43",
	  "dohr": "12:41",
	  "asr": "16:05",
	  "magreb": "18:42",
	  "icha": "19:58"
	 },
	 {
	  "fajr": "5:20",
	  "cherouk": "6:43",
	  "dohr": "12:41",
	  "asr": "16:04",
	  "magreb": "18:41",
	  "icha": "19:56"
	 },
	 {
	  "fajr": "5:20",
	  "cherouk": "6:44",
	  "dohr": "12:40",
	  "asr": "16:03",
	  "magreb": "18:39",
	  "icha": "19:55"
	 },
	 {
	  "fajr": "5:21",
	  "cherouk": "6:45",
	  "dohr": "12:40",
	  "asr": "16:02",
	  "magreb": "18:38",
	  "icha": "19:54"
	 },
	 {
	  "fajr": "5:22",
	  "cherouk": "6:46",
	  "dohr": "12:40",
	  "asr": "16:01",
	  "magreb": "18:36",
	  "icha": "19:52"
	 },
	 {
	  "fajr": "5:23",
	  "cherouk": "6:46",
	  "dohr": "12:40",
	  "asr": "16:00",
	  "magreb": "18:35",
	  "icha": "19:51"
	 },
	 {
	  "fajr": "5:23",
	  "cherouk": "6:47",
	  "dohr": "12:39",
	  "asr": "15:59",
	  "magreb": "18:34",
	  "icha": "19:49"
	 },
	 {
	  "fajr": "5:24",
	  "cherouk": "6:48",
	  "dohr": "12:39",
	  "asr": "15:58",
	  "magreb": "18:32",
	  "icha": "19:48"
	 },
	 {
	  "fajr": "5:25",
	  "cherouk": "6:49",
	  "dohr": "12:39",
	  "asr": "15:57",
	  "magreb": "18:31",
	  "icha": "19:47"
	 },
	 {
	  "fajr": "5:26",
	  "cherouk": "6:49",
	  "dohr": "12:38",
	  "asr": "15:56",
	  "magreb": "18:30",
	  "icha": "19:45"
	 },
	 {
	  "fajr": "5:27",
	  "cherouk": "6:50",
	  "dohr": "12:38",
	  "asr": "15:55",
	  "magreb": "18:28",
	  "icha": "19:44"
	 },
	 {
	  "fajr": "5:27",
	  "cherouk": "6:51",
	  "dohr": "12:38",
	  "asr": "15:54",
	  "magreb": "18:27",
	  "icha": "19:43"
	 },
	 {
	  "fajr": "5:28",
	  "cherouk": "6:52",
	  "dohr": "12:37",
	  "asr": "15:53",
	  "magreb": "18:26",
	  "icha": "19:41"
	 },
	 {
	  "fajr": "5:29",
	  "cherouk": "6:53",
	  "dohr": "12:37",
	  "asr": "15:52",
	  "magreb": "18:24",
	  "icha": "19:40"
	 },
	 {
	  "fajr": "5:30",
	  "cherouk": "6:53",
	  "dohr": "12:37",
	  "asr": "15:51",
	  "magreb": "18:23",
	  "icha": "19:39"
	 },
	 {
	  "fajr": "5:30",
	  "cherouk": "6:54",
	  "dohr": "12:37",
	  "asr": "15:50",
	  "magreb": "18:22",
	  "icha": "19:37"
	 },
	 {
	  "fajr": "5:31",
	  "cherouk": "6:55",
	  "dohr": "12:36",
	  "asr": "15:50",
	  "magreb": "18:20",
	  "icha": "19:36"
	 },
	 {
	  "fajr": "5:32",
	  "cherouk": "6:56",
	  "dohr": "12:36",
	  "asr": "15:49",
	  "magreb": "18:19",
	  "icha": "19:35"
	 },
	 {
	  "fajr": "5:33",
	  "cherouk": "6:57",
	  "dohr": "12:36",
	  "asr": "15:48",
	  "magreb": "18:18",
	  "icha": "19:34"
	 },
	 {
	  "fajr": "5:34",
	  "cherouk": "6:58",
	  "dohr": "12:36",
	  "asr": "15:47",
	  "magreb": "18:17",
	  "icha": "19:33"
	 },
	 {
	  "fajr": "5:34",
	  "cherouk": "6:58",
	  "dohr": "12:36",
	  "asr": "15:46",
	  "magreb": "18:15",
	  "icha": "19:31"
	 },
	 {
	  "fajr": "5:35",
	  "cherouk": "6:59",
	  "dohr": "12:35",
	  "asr": "15:45",
	  "magreb": "18:14",
	  "icha": "19:30"
	 },
	 {
	  "fajr": "5:36",
	  "cherouk": "7:00",
	  "dohr": "12:35",
	  "asr": "15:44",
	  "magreb": "18:13",
	  "icha": "19:29"
	 },
	 {
	  "fajr": "5:37",
	  "cherouk": "7:01",
	  "dohr": "12:35",
	  "asr": "15:43",
	  "magreb": "18:12",
	  "icha": "19:28"
	 },
	 {
	  "fajr": "5:37",
	  "cherouk": "7:02",
	  "dohr": "12:35",
	  "asr": "15:42",
	  "magreb": "18:11",
	  "icha": "19:27"
	 },
	 {
	  "fajr": "5:38",
	  "cherouk": "7:03",
	  "dohr": "12:35",
	  "asr": "15:41",
	  "magreb": "18:09",
	  "icha": "19:26"
	 },
	 {
	  "fajr": "5:39",
	  "cherouk": "7:04",
	  "dohr": "12:35",
	  "asr": "15:40",
	  "magreb": "18:08",
	  "icha": "19:25"
	 },
	 {
	  "fajr": "5:40",
	  "cherouk": "7:04",
	  "dohr": "12:35",
	  "asr": "15:40",
	  "magreb": "18:07",
	  "icha": "19:24"
	 },
	 {
	  "fajr": "5:41",
	  "cherouk": "7:05",
	  "dohr": "12:34",
	  "asr": "15:39",
	  "magreb": "18:06",
	  "icha": "19:23"
	 },
	 {
	  "fajr": "5:41",
	  "cherouk": "7:06",
	  "dohr": "12:34",
	  "asr": "15:38",
	  "magreb": "18:05",
	  "icha": "19:22"
	 },
	 {
	  "fajr": "5:42",
	  "cherouk": "7:07",
	  "dohr": "12:34",
	  "asr": "15:37",
	  "magreb": "18:04",
	  "icha": "19:21"
	 },
	 {
	  "fajr": "5:43",
	  "cherouk": "7:08",
	  "dohr": "12:34",
	  "asr": "15:36",
	  "magreb": "18:03",
	  "icha": "19:20"
	 },
	 {
	  "fajr": "5:44",
	  "cherouk": "7:09",
	  "dohr": "12:34",
	  "asr": "15:35",
	  "magreb": "18:02",
	  "icha": "19:19"
	 },
	 {
	  "fajr": "5:45",
	  "cherouk": "7:10",
	  "dohr": "12:34",
	  "asr": "15:35",
	  "magreb": "18:01",
	  "icha": "19:18"
	 },
	 {
	  "fajr": "5:45",
	  "cherouk": "7:11",
	  "dohr": "12:34",
	  "asr": "15:34",
	  "magreb": "18:00",
	  "icha": "19:17"
	 },
	 {
	  "fajr": "5:46",
	  "cherouk": "7:12",
	  "dohr": "12:34",
	  "asr": "15:33",
	  "magreb": "17:59",
	  "icha": "19:16"
	 },
	 {
	  "fajr": "5:47",
	  "cherouk": "7:13",
	  "dohr": "12:34",
	  "asr": "15:32",
	  "magreb": "17:58",
	  "icha": "19:16"
	 },
	 {
	  "fajr": "5:48",
	  "cherouk": "7:14",
	  "dohr": "12:34",
	  "asr": "15:32",
	  "magreb": "17:57",
	  "icha": "19:15"
	 },
	 {
	  "fajr": "5:49",
	  "cherouk": "7:15",
	  "dohr": "12:34",
	  "asr": "15:31",
	  "magreb": "17:56",
	  "icha": "19:14"
	 },
	 {
	  "fajr": "5:50",
	  "cherouk": "7:15",
	  "dohr": "12:34",
	  "asr": "15:30",
	  "magreb": "17:55",
	  "icha": "19:13"
	 },
	 {
	  "fajr": "5:50",
	  "cherouk": "7:16",
	  "dohr": "12:34",
	  "asr": "15:30",
	  "magreb": "17:54",
	  "icha": "19:13"
	 },
	 {
	  "fajr": "5:51",
	  "cherouk": "7:17",
	  "dohr": "12:34",
	  "asr": "15:29",
	  "magreb": "17:54",
	  "icha": "19:12"
	 },
	 {
	  "fajr": "5:52",
	  "cherouk": "7:18",
	  "dohr": "12:34",
	  "asr": "15:28",
	  "magreb": "17:53",
	  "icha": "19:11"
	 },
	 {
	  "fajr": "5:53",
	  "cherouk": "7:19",
	  "dohr": "12:34",
	  "asr": "15:28",
	  "magreb": "17:52",
	  "icha": "19:10"
	 },
	 {
	  "fajr": "5:54",
	  "cherouk": "7:20",
	  "dohr": "12:34",
	  "asr": "15:27",
	  "magreb": "17:51",
	  "icha": "19:10"
	 },
	 {
	  "fajr": "5:55",
	  "cherouk": "7:21",
	  "dohr": "12:35",
	  "asr": "15:27",
	  "magreb": "17:51",
	  "icha": "19:09"
	 },
	 {
	  "fajr": "5:55",
	  "cherouk": "7:22",
	  "dohr": "12:35",
	  "asr": "15:26",
	  "magreb": "17:50",
	  "icha": "19:09"
	 },
	 {
	  "fajr": "5:56",
	  "cherouk": "7:23",
	  "dohr": "12:35",
	  "asr": "15:26",
	  "magreb": "17:49",
	  "icha": "19:08"
	 },
	 {
	  "fajr": "5:57",
	  "cherouk": "7:24",
	  "dohr": "12:35",
	  "asr": "15:25",
	  "magreb": "17:49",
	  "icha": "19:08"
	 },
	 {
	  "fajr": "5:58",
	  "cherouk": "7:25",
	  "dohr": "12:35",
	  "asr": "15:25",
	  "magreb": "17:48",
	  "icha": "19:07"
	 },
	 {
	  "fajr": "5:59",
	  "cherouk": "7:26",
	  "dohr": "12:35",
	  "asr": "15:24",
	  "magreb": "17:47",
	  "icha": "19:07"
	 },
	 {
	  "fajr": "6:00",
	  "cherouk": "7:27",
	  "dohr": "12:36",
	  "asr": "15:24",
	  "magreb": "17:47",
	  "icha": "19:06"
	 },
	 {
	  "fajr": "6:00",
	  "cherouk": "7:28",
	  "dohr": "12:36",
	  "asr": "15:24",
	  "magreb": "17:46",
	  "icha": "19:06"
	 },
	 {
	  "fajr": "6:01",
	  "cherouk": "7:29",
	  "dohr": "12:36",
	  "asr": "15:23",
	  "magreb": "17:46",
	  "icha": "19:06"
	 },
	 {
	  "fajr": "6:02",
	  "cherouk": "7:30",
	  "dohr": "12:36",
	  "asr": "15:23",
	  "magreb": "17:45",
	  "icha": "19:05"
	 },
	 {
	  "fajr": "6:03",
	  "cherouk": "7:31",
	  "dohr": "12:37",
	  "asr": "15:23",
	  "magreb": "17:45",
	  "icha": "19:05"
	 },
	 {
	  "fajr": "6:04",
	  "cherouk": "7:32",
	  "dohr": "12:37",
	  "asr": "15:22",
	  "magreb": "17:45",
	  "icha": "19:05"
	 },
	 {
	  "fajr": "6:04",
	  "cherouk": "7:33",
	  "dohr": "12:37",
	  "asr": "15:22",
	  "magreb": "17:44",
	  "icha": "19:05"
	 },
	 {
	  "fajr": "6:05",
	  "cherouk": "7:33",
	  "dohr": "12:37",
	  "asr": "15:22",
	  "magreb": "17:44",
	  "icha": "19:04"
	 },
	 {
	  "fajr": "6:06",
	  "cherouk": "7:34",
	  "dohr": "12:38",
	  "asr": "15:22",
	  "magreb": "17:44",
	  "icha": "19:04"
	 },
	 {
	  "fajr": "6:07",
	  "cherouk": "7:35",
	  "dohr": "12:38",
	  "asr": "15:21",
	  "magreb": "17:43",
	  "icha": "19:04"
	 },
	 {
	  "fajr": "6:08",
	  "cherouk": "7:35",
	  "dohr": "12:38",
	  "asr": "15:21",
	  "magreb": "17:43",
	  "icha": "19:04"
	 },
	 {
	  "fajr": "6:08",
	  "cherouk": "7:36",
	  "dohr": "12:39",
	  "asr": "15:21",
	  "magreb": "17:43",
	  "icha": "19:04"
	 },
	 {
	  "fajr": "6:09",
	  "cherouk": "7:37",
	  "dohr": "12:39",
	  "asr": "15:21",
	  "magreb": "17:43",
	  "icha": "19:04"
	 },
	 {
	  "fajr": "6:10",
	  "cherouk": "7:38",
	  "dohr": "12:39",
	  "asr": "15:21",
	  "magreb": "17:43",
	  "icha": "19:04"
	 },
	 {
	  "fajr": "6:11",
	  "cherouk": "7:39",
	  "dohr": "12:40",
	  "asr": "15:21",
	  "magreb": "17:42",
	  "icha": "19:04"
	 },
	 {
	  "fajr": "6:12",
	  "cherouk": "7:40",
	  "dohr": "12:40",
	  "asr": "15:21",
	  "magreb": "17:42",
	  "icha": "19:04"
	 },
	 {
	  "fajr": "6:12",
	  "cherouk": "7:41",
	  "dohr": "12:41",
	  "asr": "15:21",
	  "magreb": "17:42",
	  "icha": "19:04"
	 },
	 {
	  "fajr": "6:13",
	  "cherouk": "7:42",
	  "dohr": "12:41",
	  "asr": "15:21",
	  "magreb": "17:42",
	  "icha": "19:04"
	 },
	 {
	  "fajr": "6:14",
	  "cherouk": "7:42",
	  "dohr": "12:42",
	  "asr": "15:21",
	  "magreb": "17:42",
	  "icha": "19:04"
	 },
	 {
	  "fajr": "6:15",
	  "cherouk": "7:43",
	  "dohr": "12:42",
	  "asr": "15:21",
	  "magreb": "17:42",
	  "icha": "19:04"
	 },
	 {
	  "fajr": "6:15",
	  "cherouk": "7:44",
	  "dohr": "12:42",
	  "asr": "15:21",
	  "magreb": "17:42",
	  "icha": "19:04"
	 },
	 {
	  "fajr": "6:16",
	  "cherouk": "7:45",
	  "dohr": "12:43",
	  "asr": "15:21",
	  "magreb": "17:43",
	  "icha": "19:04"
	 },
	 {
	  "fajr": "6:17",
	  "cherouk": "7:46",
	  "dohr": "12:43",
	  "asr": "15:22",
	  "magreb": "17:43",
	  "icha": "19:05"
	 },
	 {
	  "fajr": "6:17",
	  "cherouk": "7:46",
	  "dohr": "12:44",
	  "asr": "15:22",
	  "magreb": "17:43",
	  "icha": "19:05"
	 },
	 {
	  "fajr": "6:18",
	  "cherouk": "7:47",
	  "dohr": "12:44",
	  "asr": "15:22",
	  "magreb": "17:43",
	  "icha": "19:05"
	 },
	 {
	  "fajr": "6:19",
	  "cherouk": "7:48",
	  "dohr": "12:45",
	  "asr": "15:22",
	  "magreb": "17:43",
	  "icha": "19:05"
	 },
	 {
	  "fajr": "6:19",
	  "cherouk": "7:49",
	  "dohr": "12:45",
	  "asr": "15:23",
	  "magreb": "17:44",
	  "icha": "19:06"
	 },
	 {
	  "fajr": "6:20",
	  "cherouk": "7:49",
	  "dohr": "12:46",
	  "asr": "15:23",
	  "magreb": "17:44",
	  "icha": "19:06"
	 },
	 {
	  "fajr": "6:21",
	  "cherouk": "7:50",
	  "dohr": "12:46",
	  "asr": "15:23",
	  "magreb": "17:44",
	  "icha": "19:06"
	 },
	 {
	  "fajr": "6:21",
	  "cherouk": "7:50",
	  "dohr": "12:47",
	  "asr": "15:24",
	  "magreb": "17:45",
	  "icha": "19:07"
	 },
	 {
	  "fajr": "6:22",
	  "cherouk": "7:51",
	  "dohr": "12:47",
	  "asr": "15:24",
	  "magreb": "17:45",
	  "icha": "19:07"
	 },
	 {
	  "fajr": "6:22",
	  "cherouk": "7:52",
	  "dohr": "12:48",
	  "asr": "15:25",
	  "magreb": "17:45",
	  "icha": "19:08"
	 },
	 {
	  "fajr": "6:23",
	  "cherouk": "7:52",
	  "dohr": "12:48",
	  "asr": "15:25",
	  "magreb": "17:46",
	  "icha": "19:08"
	 },
	 {
	  "fajr": "6:23",
	  "cherouk": "7:53",
	  "dohr": "12:49",
	  "asr": "15:26",
	  "magreb": "17:46",
	  "icha": "19:09"
	 },
	 {
	  "fajr": "6:24",
	  "cherouk": "7:53",
	  "dohr": "12:49",
	  "asr": "15:26",
	  "magreb": "17:47",
	  "icha": "19:09"
	 },
	 {
	  "fajr": "6:24",
	  "cherouk": "7:54",
	  "dohr": "12:50",
	  "asr": "15:27",
	  "magreb": "17:47",
	  "icha": "19:10"
	 },
	 {
	  "fajr": "6:25",
	  "cherouk": "7:54",
	  "dohr": "12:50",
	  "asr": "15:27",
	  "magreb": "17:48",
	  "icha": "19:10"
	 },
	 {
	  "fajr": "6:25",
	  "cherouk": "7:56",
	  "dohr": "12:51",
	  "asr": "15:28",
	  "magreb": "17:49",
	  "icha": "19:11"
	 },
	 {
	  "fajr": "6:26",
	  "cherouk": "7:56",
	  "dohr": "12:51",
	  "asr": "15:28",
	  "magreb": "17:49",
	  "icha": "19:11"
	 },
	 {
	  "fajr": "6:26",
	  "cherouk": "7:56",
	  "dohr": "12:52",
	  "asr": "15:29",
	  "magreb": "17:50",
	  "icha": "19:12"
	 },
	 {
	  "fajr": "6:26",
	  "cherouk": "7:57",
	  "dohr": "12:52",
	  "asr": "15:29",
	  "magreb": "17:50",
	  "icha": "19:13"
	 },
	 {
	  "fajr": "6:27",
	  "cherouk": "7:57",
	  "dohr": "12:52",
	  "asr": "15:30",
	  "magreb": "17:51",
	  "icha": "19:13"
	 },
	 {
	  "fajr": "6:27",
	  "cherouk": "7:57",
	  "dohr": "12:53",
	  "asr": "15:31",
	  "magreb": "17:52",
	  "icha": "19:14"
	 },
	 {
	  "fajr": "6:27",
	  "cherouk": "7:57",
	  "dohr": "12:53",
	  "asr": "15:31",
	  "magreb": "17:53",
	  "icha": "19:15"
	 }
	]
}
